contextdata/__init__.py
contextdata/context.py
contextdata/context_logfilter.py
contextdata/py.typed
contextdata-0.2.1.dist-info/LICENSE
contextdata-0.2.1.dist-info/METADATA
contextdata-0.2.1.dist-info/WHEEL
contextdata-0.2.1.dist-info/top_level.txt
contextdata-0.2.1.dist-info/RECORD
